lightweight_charts/__init__.py
lightweight_charts/abstract.py
lightweight_charts/chart.py
lightweight_charts/drawings.py
lightweight_charts/polygon.py
lightweight_charts/table.py
lightweight_charts/toolbox.py
lightweight_charts/topbar.py
lightweight_charts/util.py
lightweight_charts/widgets.py
lightweight_charts/js/bundle.js
lightweight_charts/js/index.html
lightweight_charts/js/lightweight-charts.js
lightweight_charts/js/styles.css
plutus_lightweight_charts-2.2.0.dist-info/LICENSE
plutus_lightweight_charts-2.2.0.dist-info/METADATA
plutus_lightweight_charts-2.2.0.dist-info/WHEEL
plutus_lightweight_charts-2.2.0.dist-info/top_level.txt
plutus_lightweight_charts-2.2.0.dist-info/RECORD
