Metadata-Version: 2.1
Name: plutus_lightweight_charts
Version: 2.2.0
Summary: Fork of lightweight-charts-python with Plutus specific enchancements.
Home-page: https://github.com/plutus-terminal/plutus-lightweight-charts-python
Author: plutus
License: MIT
Requires-Python: >=3.8
License-File: LICENSE
Requires-Dist: pandas
Requires-Dist: pywebview>=5.0.5
